pytrace_live/__init__.py
pytrace_live/cli.py
pytrace_live/tracer.py
pytrace_live-1.0.0.dist-info/licenses/LICENSE
pytrace_live-1.0.0.dist-info/METADATA
pytrace_live-1.0.0.dist-info/WHEEL
pytrace_live-1.0.0.dist-info/entry_points.txt
pytrace_live-1.0.0.dist-info/top_level.txt
pytrace_live-1.0.0.dist-info/RECORD
