Metadata-Version: 2.4
Name: pytrace-live
Version: 1.0.0
Summary: Live Python function execution tracer with timing and slow function detection
Author-email: Python Tooling Engineer <engineer@example.com>
License: MIT
Project-URL: Homepage, https://github.com/yourusername/pytrace-live
Project-URL: Repository, https://github.com/yourusername/pytrace-live
Keywords: tracing,profiling,performance,debugging,cli
Classifier: Development Status :: 4 - Beta
Classifier: Intended Audience :: Developers
Classifier: License :: OSI Approved :: MIT License
Classifier: Programming Language :: Python :: 3
Classifier: Programming Language :: Python :: 3.9
Classifier: Programming Language :: Python :: 3.10
Classifier: Programming Language :: Python :: 3.11
Classifier: Programming Language :: Python :: 3.12
Classifier: Topic :: Software Development :: Debuggers
Classifier: Topic :: Software Development :: Testing
Requires-Python: >=3.9
License-File: LICENSE
Requires-Dist: rich>=10.0.0
Dynamic: license-file
